projd
