Metadata-Version: 1.1
Name: projd
Version: 0.1.0
Summary: Utilities for working with projects and applications organized within a root directory.
Home-page: https://github.com/todddeluca/projd
Author: Todd Francis DeLuca
Author-email: todddeluca@yahoo.com
License: MIT
Keywords: python project directory application
Platform: UNKNOWN
Classifier: License :: OSI Approved :: MIT License
Classifier: Development Status :: 3 - Alpha
Classifier: Programming Language :: Python :: 2
Classifier: Programming Language :: Python :: 2.7
